krug/__init__.py
krug/_optim_types.py
krug/ga/__init__.py
krug/ga/_ga.py
krug/sa/__init__.py
krug/sa/_sa.py
krug-0.0.12.dist-info/LICENSE
krug-0.0.12.dist-info/METADATA
krug-0.0.12.dist-info/WHEEL
krug-0.0.12.dist-info/top_level.txt
krug-0.0.12.dist-info/RECORD
