Metadata-Version: 2.1
Name: krug
Version: 0.0.12
Summary: A collection of useful heuristic based optimization algorithms.
Home-page: UNKNOWN
Author: Alexander Anthon
License: GNU GPLv3
Platform: UNKNOWN
Classifier: Programming Language :: Python :: 3
Requires-Dist: numpy
